nua_sdk/__init__.py
nua_sdk/authentication_agent/__init__.py
nua_sdk/authentication_agent/main.py
nua_sdk-1.1.9.dist-info/METADATA
nua_sdk-1.1.9.dist-info/WHEEL
nua_sdk-1.1.9.dist-info/top_level.txt
nua_sdk-1.1.9.dist-info/RECORD
