Metadata-Version: 2.1
Name: nua-sdk
Version: 1.1.9
Summary: SDK for NUA shared components
Author: NUA Team
Author-email: a.baqaleb@nuasecurity.com
Classifier: Programming Language :: Python :: 3
Classifier: License :: OSI Approved :: MIT License
Classifier: Operating System :: OS Independent
Requires-Python: >=3.9
